toml_adapt/AllShapes.py
toml_adapt/CargoActions.py
toml_adapt/Common.py
toml_adapt/DocumentOperations.py
toml_adapt/DocumentType.py
toml_adapt/FlitActions.py
toml_adapt/ManipulateToml.py
toml_adapt/Match.py
toml_adapt/PoetryActions.py
toml_adapt/Shape.py
toml_adapt/ToolExtraction.py
toml_adapt/__init__.py
toml_adapt/main.py
toml_adapt-0.3.4.dist-info/AUTHORS.rst
toml_adapt-0.3.4.dist-info/LICENSE
toml_adapt-0.3.4.dist-info/METADATA
toml_adapt-0.3.4.dist-info/WHEEL
toml_adapt-0.3.4.dist-info/entry_points.txt
toml_adapt-0.3.4.dist-info/RECORD
