Metadata-Version: 2.1
Name: toml-adapt
Version: 0.3.4
Summary: A simple command-line interface for manipulating toml files
Home-page: https://github.com/firefly-cpp/toml-adapt
License: MIT
Keywords: adaptation,data manipulation,flit,poetry,toml
Author: Iztok Fister Jr.
Author-email: iztok@iztok-jr-fister.eu
Requires-Python: >=3.10,<4.0
Classifier: License :: OSI Approved :: MIT License
Classifier: Programming Language :: Python :: 3
Classifier: Programming Language :: Python :: 3.10
Classifier: Programming Language :: Python :: 3.11
Classifier: Programming Language :: Python :: 3.12
Provides-Extra: docs
Requires-Dist: click
Requires-Dist: toml
Project-URL: Documentation, https://toml-adapt.readthedocs.io/en/latest/
Project-URL: Repository, https://github.com/firefly-cpp/toml-adapt
